{
  "trace_id": "trace_1763270429704",
  "operation": "research_operation",
  "start_time": "2025-11-16T10:50:29.704289",
  "metadata": {
    "topic": "chat gpt",
    "type": "Academic",
    "max_results": 5
  },
  "spans": [
    {
      "agent": "ResearchAgent",
      "action": "search",
      "duration": 2.1966793537139893,
      "status": "success",
      "timestamp": "2025-11-16T10:50:31.905818"
    },
    {
      "agent": "SummarizerAgent",
      "action": "summarize",
      "duration": 0.002427339553833008,
      "status": "success",
      "timestamp": "2025-11-16T10:50:31.911750"
    },
    {
      "agent": "ReportGenerator",
      "action": "generate",
      "duration": 0.0009970664978027344,
      "status": "success",
      "timestamp": "2025-11-16T10:50:31.914748"
    },
    {
      "agent": "AccessibilityAgent",
      "action": "make_accessible",
      "duration": 0.0021653175354003906,
      "status": "success",
      "timestamp": "2025-11-16T10:50:31.918347"
    },
    {
      "agent": "TextToSpeechAgent",
      "action": "prepare_speech",
      "duration": 0.0029997825622558594,
      "status": "success",
      "timestamp": "2025-11-16T10:50:31.923348"
    }
  ],
  "status": "success",
  "end_time": "2025-11-16T10:50:31.943346",
  "total_duration": 2.239057
}